{
  "generated_at": "2026-04-26T13:21:58",
  "sample_rows": 1000,
  "variants": {
    "GB0": {
      "rows": 125,
      "file_qrel_coverage": 1.0,
      "page_qrel_coverage": 1.0,
      "chunk_qrel_coverage": 0.696,
      "root_qrel_coverage": 0.696,
      "chunk_qrel_rows": 87,
      "root_qrel_rows": 87,
      "hit_at_5": 0.296,
      "initial_retrieval_hit_at_5": 0.672,
      "final_retrieval_hit_at_5": 0.672,
      "file_hit_at_5": 0.744,
      "file_page_hit_at_5": 0.504,
      "page_hit_at_5": 0.608,
      "chunk_hit_at_5": 0.0,
      "root_hit_at_5": 0.5287356321839081,
      "chunk_mrr": 0.0,
      "root_mrr": 0.39233716475095787,
      "answer_support_hit_at_5_experimental": 0.5172413793103449,
      "anchor_hit_at_5": 0.256,
      "keyword_hit_at_5": 0.904,
      "keyword_required_hit_at_5": 0.648,
      "legacy_chunk_hit_at_5": 0.0,
      "mrr": 0.296,
      "positive_chunk_mrr": 0.0,
      "context_precision_id_at_5": 0.2432,
      "id_context_precision_at_5": 0.104,
      "id_context_recall_at_5": 0.52,
      "ndcg_at_5": 0.39317454461806545,
      "map_at_5": 0.38706666666666667,
      "irrelevant_context_ratio_at_5": 0.7567999999999999,
      "hard_negative_file_hit_at_5": 0.136,
      "hard_negative_context_ratio_at_5": 0.027200000000000002,
      "weak_any_candidate_recall_before_rerank": 0.832,
      "candidate_recall_before_rerank": 0.832,
      "file_candidate_recall_before_rerank": 0.952,
      "rerank_drop_rate": 0.168,
      "file_rerank_drop_rate": 0.208,
      "structure_drop_rate": 0.0,
      "file_structure_drop_rate": 0.0,
      "file_rank_before_rerank_p50": 2.0,
      "file_rank_before_rerank_p95": 26.0,
      "recall_at_5": 0.6007906759906759,
      "avg_latency_ms": 1140.1391472003888,
      "p50_latency_ms": 939.0925000043353,
      "p95_latency_ms": 1060.972780000884,
      "retrieval_p50_ms": 939.0925000043353,
      "retrieval_p95_ms": 1060.972780000884,
      "error_rate": 0.0,
      "fallback_trigger_rate": 0.0,
      "fallback_executed_rate": 0.0,
      "fallback_helped_rate": 0.0,
      "fallback_hurt_rate": 0.0,
      "faithfulness_score": null,
      "answer_relevance_score": null,
      "citation_coverage": null,
      "answer_eval_error_rate": null,
      "rewrite_strategy_distribution": {
        "none": 125
      }
    },
    "GS1": {
      "rows": 125,
      "file_qrel_coverage": 1.0,
      "page_qrel_coverage": 1.0,
      "chunk_qrel_coverage": 0.696,
      "root_qrel_coverage": 0.696,
      "chunk_qrel_rows": 87,
      "root_qrel_rows": 87,
      "hit_at_5": 0.296,
      "initial_retrieval_hit_at_5": 0.672,
      "final_retrieval_hit_at_5": 0.672,
      "file_hit_at_5": 0.744,
      "file_page_hit_at_5": 0.504,
      "page_hit_at_5": 0.608,
      "chunk_hit_at_5": 0.0,
      "root_hit_at_5": 0.5287356321839081,
      "chunk_mrr": 0.0,
      "root_mrr": 0.39233716475095787,
      "answer_support_hit_at_5_experimental": 0.5172413793103449,
      "anchor_hit_at_5": 0.256,
      "keyword_hit_at_5": 0.904,
      "keyword_required_hit_at_5": 0.648,
      "legacy_chunk_hit_at_5": 0.0,
      "mrr": 0.296,
      "positive_chunk_mrr": 0.0,
      "context_precision_id_at_5": 0.2432,
      "id_context_precision_at_5": 0.1044,
      "id_context_recall_at_5": 0.52,
      "ndcg_at_5": 0.39317454461806545,
      "map_at_5": 0.38706666666666667,
      "irrelevant_context_ratio_at_5": 0.7567999999999999,
      "hard_negative_file_hit_at_5": 0.136,
      "hard_negative_context_ratio_at_5": 0.027200000000000002,
      "weak_any_candidate_recall_before_rerank": 0.832,
      "candidate_recall_before_rerank": 0.832,
      "file_candidate_recall_before_rerank": 0.952,
      "rerank_drop_rate": 0.168,
      "file_rerank_drop_rate": 0.208,
      "structure_drop_rate": 0.0,
      "file_structure_drop_rate": 0.0,
      "file_rank_before_rerank_p50": 2.0,
      "file_rank_before_rerank_p95": 26.0,
      "recall_at_5": 0.6007906759906759,
      "avg_latency_ms": 1061.4962751996936,
      "p50_latency_ms": 822.5651999964612,
      "p95_latency_ms": 1037.84064000356,
      "retrieval_p50_ms": 822.5651999964612,
      "retrieval_p95_ms": 1037.84064000356,
      "error_rate": 0.0,
      "fallback_trigger_rate": 0.0,
      "fallback_executed_rate": 0.0,
      "fallback_helped_rate": 0.0,
      "fallback_hurt_rate": 0.0,
      "faithfulness_score": null,
      "answer_relevance_score": null,
      "citation_coverage": null,
      "answer_eval_error_rate": null,
      "rewrite_strategy_distribution": {
        "none": 125
      }
    },
    "GS2": {
      "rows": 125,
      "file_qrel_coverage": 1.0,
      "page_qrel_coverage": 1.0,
      "chunk_qrel_coverage": 0.696,
      "root_qrel_coverage": 0.696,
      "chunk_qrel_rows": 87,
      "root_qrel_rows": 87,
      "hit_at_5": 0.304,
      "initial_retrieval_hit_at_5": 0.768,
      "final_retrieval_hit_at_5": 0.768,
      "file_hit_at_5": 0.872,
      "file_page_hit_at_5": 0.68,
      "page_hit_at_5": 0.792,
      "chunk_hit_at_5": 0.0,
      "root_hit_at_5": 0.6436781609195402,
      "chunk_mrr": 0.0,
      "root_mrr": 0.5078544061302681,
      "answer_support_hit_at_5_experimental": 0.632183908045977,
      "anchor_hit_at_5": 0.344,
      "keyword_hit_at_5": 0.968,
      "keyword_required_hit_at_5": 0.752,
      "legacy_chunk_hit_at_5": 0.0,
      "mrr": 0.304,
      "positive_chunk_mrr": 0.0,
      "context_precision_id_at_5": 0.288,
      "id_context_precision_at_5": 0.14320000000000002,
      "id_context_recall_at_5": 0.712,
      "ndcg_at_5": 0.5503869431302787,
      "map_at_5": 0.5557333333333333,
      "irrelevant_context_ratio_at_5": 0.712,
      "hard_negative_file_hit_at_5": 0.024,
      "hard_negative_context_ratio_at_5": 0.0064,
      "weak_any_candidate_recall_before_rerank": 0.912,
      "candidate_recall_before_rerank": 0.912,
      "file_candidate_recall_before_rerank": 1.0,
      "rerank_drop_rate": 0.144,
      "file_rerank_drop_rate": 0.128,
      "structure_drop_rate": 0.0,
      "file_structure_drop_rate": 0.0,
      "file_rank_before_rerank_p50": 1.0,
      "file_rank_before_rerank_p95": 10.0,
      "recall_at_5": 0.7204893772893773,
      "avg_latency_ms": 1074.0575968002668,
      "p50_latency_ms": 847.2201999975368,
      "p95_latency_ms": 1058.0255199951353,
      "retrieval_p50_ms": 847.2201999975368,
      "retrieval_p95_ms": 1058.0255199951353,
      "error_rate": 0.0,
      "fallback_trigger_rate": 0.0,
      "fallback_executed_rate": 0.0,
      "fallback_helped_rate": 0.0,
      "fallback_hurt_rate": 0.0,
      "faithfulness_score": null,
      "answer_relevance_score": null,
      "citation_coverage": null,
      "answer_eval_error_rate": null,
      "rewrite_strategy_distribution": {
        "none": 125
      }
    },
    "GS2H": {
      "rows": 125,
      "file_qrel_coverage": 1.0,
      "page_qrel_coverage": 1.0,
      "chunk_qrel_coverage": 0.696,
      "root_qrel_coverage": 0.696,
      "chunk_qrel_rows": 87,
      "root_qrel_rows": 87,
      "hit_at_5": 0.304,
      "initial_retrieval_hit_at_5": 0.728,
      "final_retrieval_hit_at_5": 0.728,
      "file_hit_at_5": 0.864,
      "file_page_hit_at_5": 0.616,
      "page_hit_at_5": 0.72,
      "chunk_hit_at_5": 0.0,
      "root_hit_at_5": 0.6091954022988506,
      "chunk_mrr": 0.0,
      "root_mrr": 0.48007662835249043,
      "answer_support_hit_at_5_experimental": 0.5977011494252874,
      "anchor_hit_at_5": 0.336,
      "keyword_hit_at_5": 0.952,
      "keyword_required_hit_at_5": 0.744,
      "legacy_chunk_hit_at_5": 0.0,
      "mrr": 0.3,
      "positive_chunk_mrr": 0.0,
      "context_precision_id_at_5": 0.2704,
      "id_context_precision_at_5": 0.1312,
      "id_context_recall_at_5": 0.648,
      "ndcg_at_5": 0.5030622140345528,
      "map_at_5": 0.5094666666666666,
      "irrelevant_context_ratio_at_5": 0.7296,
      "hard_negative_file_hit_at_5": 0.024,
      "hard_negative_context_ratio_at_5": 0.0064,
      "weak_any_candidate_recall_before_rerank": 0.912,
      "candidate_recall_before_rerank": 0.912,
      "file_candidate_recall_before_rerank": 1.0,
      "rerank_drop_rate": 0.184,
      "file_rerank_drop_rate": 0.136,
      "structure_drop_rate": 0.0,
      "file_structure_drop_rate": 0.0,
      "file_rank_before_rerank_p50": 5.0,
      "file_rank_before_rerank_p95": 17.799999999999997,
      "recall_at_5": 0.6946307914307914,
      "avg_latency_ms": 1041.6360431998037,
      "p50_latency_ms": 835.782800000743,
      "p95_latency_ms": 930.333779999637,
      "retrieval_p50_ms": 835.782800000743,
      "retrieval_p95_ms": 930.333779999637,
      "error_rate": 0.0,
      "fallback_trigger_rate": 0.0,
      "fallback_executed_rate": 0.0,
      "fallback_helped_rate": 0.0,
      "fallback_hurt_rate": 0.0,
      "faithfulness_score": null,
      "answer_relevance_score": null,
      "citation_coverage": null,
      "answer_eval_error_rate": null,
      "rewrite_strategy_distribution": {
        "none": 125
      }
    },
    "GS2HR": {
      "rows": 125,
      "file_qrel_coverage": 1.0,
      "page_qrel_coverage": 1.0,
      "chunk_qrel_coverage": 0.696,
      "root_qrel_coverage": 0.696,
      "chunk_qrel_rows": 87,
      "root_qrel_rows": 87,
      "hit_at_5": 0.304,
      "initial_retrieval_hit_at_5": 0.848,
      "final_retrieval_hit_at_5": 0.848,
      "file_hit_at_5": 0.992,
      "file_page_hit_at_5": 0.752,
      "page_hit_at_5": 0.784,
      "chunk_hit_at_5": 0.0,
      "root_hit_at_5": 0.7701149425287356,
      "chunk_mrr": 0.0,
      "root_mrr": 0.6446360153256705,
      "answer_support_hit_at_5_experimental": 0.7586206896551724,
      "anchor_hit_at_5": 0.376,
      "keyword_hit_at_5": 0.984,
      "keyword_required_hit_at_5": 0.824,
      "legacy_chunk_hit_at_5": 0.0,
      "mrr": 0.304,
      "positive_chunk_mrr": 0.0,
      "context_precision_id_at_5": 0.2944,
      "id_context_precision_at_5": 0.16360000000000002,
      "id_context_recall_at_5": 0.808,
      "ndcg_at_5": 0.6513740459284937,
      "map_at_5": 0.6872,
      "irrelevant_context_ratio_at_5": 0.7056,
      "hard_negative_file_hit_at_5": 0.024,
      "hard_negative_context_ratio_at_5": 0.0048000000000000004,
      "weak_any_candidate_recall_before_rerank": 0.912,
      "candidate_recall_before_rerank": 0.912,
      "file_candidate_recall_before_rerank": 1.0,
      "rerank_drop_rate": 0.064,
      "file_rerank_drop_rate": 0.008,
      "structure_drop_rate": 0.0,
      "file_structure_drop_rate": 0.0,
      "file_rank_before_rerank_p50": 5.0,
      "file_rank_before_rerank_p95": 17.799999999999997,
      "recall_at_5": 0.7723929847929848,
      "avg_latency_ms": 2132.763692798908,
      "p50_latency_ms": 1531.6611000016565,
      "p95_latency_ms": 2059.9669999995967,
      "retrieval_p50_ms": 1531.6611000016565,
      "retrieval_p95_ms": 2059.9669999995967,
      "error_rate": 0.0,
      "fallback_trigger_rate": 0.0,
      "fallback_executed_rate": 0.0,
      "fallback_helped_rate": 0.0,
      "fallback_hurt_rate": 0.0,
      "faithfulness_score": null,
      "answer_relevance_score": null,
      "citation_coverage": null,
      "answer_eval_error_rate": null,
      "rewrite_strategy_distribution": {
        "none": 125
      }
    },
    "GS3": {
      "rows": 125,
      "file_qrel_coverage": 1.0,
      "page_qrel_coverage": 1.0,
      "chunk_qrel_coverage": 0.696,
      "root_qrel_coverage": 0.696,
      "chunk_qrel_rows": 87,
      "root_qrel_rows": 87,
      "hit_at_5": 0.76,
      "initial_retrieval_hit_at_5": 0.808,
      "final_retrieval_hit_at_5": 0.808,
      "file_hit_at_5": 0.92,
      "file_page_hit_at_5": 0.712,
      "page_hit_at_5": 0.752,
      "chunk_hit_at_5": 0.6551724137931034,
      "root_hit_at_5": 0.7241379310344828,
      "chunk_mrr": 0.5804597701149425,
      "root_mrr": 0.6369731800766283,
      "answer_support_hit_at_5_experimental": 0.7126436781609196,
      "anchor_hit_at_5": 0.368,
      "keyword_hit_at_5": 0.992,
      "keyword_required_hit_at_5": 0.808,
      "legacy_chunk_hit_at_5": 0.6551724137931034,
      "mrr": 0.708,
      "positive_chunk_mrr": 0.404,
      "context_precision_id_at_5": 0.38226666666666664,
      "id_context_precision_at_5": 0.15506666666666666,
      "id_context_recall_at_5": 0.76,
      "ndcg_at_5": 0.6365582254415029,
      "map_at_5": 0.6813333333333333,
      "irrelevant_context_ratio_at_5": 0.6177333333333334,
      "hard_negative_file_hit_at_5": 0.024,
      "hard_negative_context_ratio_at_5": 0.0064,
      "weak_any_candidate_recall_before_rerank": 0.912,
      "candidate_recall_before_rerank": 0.912,
      "file_candidate_recall_before_rerank": 1.0,
      "rerank_drop_rate": 0.104,
      "file_rerank_drop_rate": 0.08,
      "structure_drop_rate": 0.0,
      "file_structure_drop_rate": 0.0,
      "file_rank_before_rerank_p50": 5.0,
      "file_rank_before_rerank_p95": 22.799999999999997,
      "recall_at_5": 0.7938294372294372,
      "avg_latency_ms": 1419.5909080000129,
      "p50_latency_ms": 1144.175900000846,
      "p95_latency_ms": 1609.5243599935202,
      "retrieval_p50_ms": 1144.175900000846,
      "retrieval_p95_ms": 1609.5243599935202,
      "error_rate": 0.0,
      "fallback_trigger_rate": 0.0,
      "fallback_executed_rate": 0.0,
      "fallback_helped_rate": 0.0,
      "fallback_hurt_rate": 0.0,
      "faithfulness_score": null,
      "answer_relevance_score": null,
      "citation_coverage": null,
      "answer_eval_error_rate": null,
      "rewrite_strategy_distribution": {
        "none": 125
      }
    },
    "V3F": {
      "rows": 125,
      "file_qrel_coverage": 1.0,
      "page_qrel_coverage": 1.0,
      "chunk_qrel_coverage": 0.696,
      "root_qrel_coverage": 0.696,
      "chunk_qrel_rows": 87,
      "root_qrel_rows": 87,
      "hit_at_5": 0.328,
      "initial_retrieval_hit_at_5": 0.352,
      "final_retrieval_hit_at_5": 0.352,
      "file_hit_at_5": 0.416,
      "file_page_hit_at_5": 0.28,
      "page_hit_at_5": 0.32,
      "chunk_hit_at_5": 0.27586206896551724,
      "root_hit_at_5": 0.3103448275862069,
      "chunk_mrr": 0.21015325670498086,
      "root_mrr": 0.22835249042145594,
      "answer_support_hit_at_5_experimental": 0.3103448275862069,
      "anchor_hit_at_5": 0.168,
      "keyword_hit_at_5": 0.408,
      "keyword_required_hit_at_5": 0.32,
      "legacy_chunk_hit_at_5": 0.27586206896551724,
      "mrr": 0.28226666666666667,
      "positive_chunk_mrr": 0.14626666666666668,
      "context_precision_id_at_5": 0.1616,
      "id_context_precision_at_5": 0.0576,
      "id_context_recall_at_5": 0.288,
      "ndcg_at_5": 0.22823724374212528,
      "map_at_5": 0.21893333333333334,
      "irrelevant_context_ratio_at_5": 0.8383999999999999,
      "hard_negative_file_hit_at_5": 0.016,
      "hard_negative_context_ratio_at_5": 0.014545454545454545,
      "weak_any_candidate_recall_before_rerank": 0.424,
      "candidate_recall_before_rerank": 0.424,
      "file_candidate_recall_before_rerank": 0.44,
      "rerank_drop_rate": 0.048,
      "file_rerank_drop_rate": 0.016,
      "structure_drop_rate": 0.024,
      "file_structure_drop_rate": 0.008,
      "file_rank_before_rerank_p50": 5.0,
      "file_rank_before_rerank_p95": 24.299999999999997,
      "recall_at_5": 0.3289590187590188,
      "avg_latency_ms": 2753.1039879998425,
      "p50_latency_ms": 33.97509999922477,
      "p95_latency_ms": 3047.0336999977008,
      "retrieval_p50_ms": 33.97509999922477,
      "retrieval_p95_ms": 3047.0336999977008,
      "error_rate": 0.0,
      "fallback_trigger_rate": 0.0,
      "fallback_executed_rate": 0.0,
      "fallback_helped_rate": 0.0,
      "fallback_hurt_rate": 0.0,
      "faithfulness_score": null,
      "answer_relevance_score": null,
      "citation_coverage": null,
      "answer_eval_error_rate": null,
      "rewrite_strategy_distribution": {
        "none": 125
      }
    },
    "V3Q": {
      "rows": 125,
      "file_qrel_coverage": 1.0,
      "page_qrel_coverage": 1.0,
      "chunk_qrel_coverage": 0.696,
      "root_qrel_coverage": 0.696,
      "chunk_qrel_rows": 87,
      "root_qrel_rows": 87,
      "hit_at_5": 0.808,
      "initial_retrieval_hit_at_5": 0.864,
      "final_retrieval_hit_at_5": 0.864,
      "file_hit_at_5": 0.992,
      "file_page_hit_at_5": 0.768,
      "page_hit_at_5": 0.816,
      "chunk_hit_at_5": 0.7241379310344828,
      "root_hit_at_5": 0.7931034482758621,
      "chunk_mrr": 0.574904214559387,
      "root_mrr": 0.6348659003831417,
      "answer_support_hit_at_5_experimental": 0.7931034482758621,
      "anchor_hit_at_5": 0.368,
      "keyword_hit_at_5": 0.984,
      "keyword_required_hit_at_5": 0.84,
      "legacy_chunk_hit_at_5": 0.7241379310344828,
      "mrr": 0.7041333333333333,
      "positive_chunk_mrr": 0.40013333333333334,
      "context_precision_id_at_5": 0.3936,
      "id_context_precision_at_5": 0.1664,
      "id_context_recall_at_5": 0.832,
      "ndcg_at_5": 0.645444820176546,
      "map_at_5": 0.6752,
      "irrelevant_context_ratio_at_5": 0.6063999999999999,
      "hard_negative_file_hit_at_5": 0.024,
      "hard_negative_context_ratio_at_5": 0.008,
      "weak_any_candidate_recall_before_rerank": 0.976,
      "candidate_recall_before_rerank": 0.976,
      "file_candidate_recall_before_rerank": 1.0,
      "rerank_drop_rate": 0.04,
      "file_rerank_drop_rate": 0.008,
      "structure_drop_rate": 0.08,
      "file_structure_drop_rate": 0.0,
      "file_rank_before_rerank_p50": 14.0,
      "file_rank_before_rerank_p95": 43.8,
      "recall_at_5": 0.8340103896103896,
      "avg_latency_ms": 4135.071360800066,
      "p50_latency_ms": 3938.231000007363,
      "p95_latency_ms": 4450.32883999811,
      "retrieval_p50_ms": 3938.231000007363,
      "retrieval_p95_ms": 4450.32883999811,
      "error_rate": 0.0,
      "fallback_trigger_rate": 0.0,
      "fallback_executed_rate": 0.0,
      "fallback_helped_rate": 0.0,
      "fallback_hurt_rate": 0.0,
      "faithfulness_score": null,
      "answer_relevance_score": null,
      "citation_coverage": null,
      "answer_eval_error_rate": null,
      "rewrite_strategy_distribution": {
        "none": 125
      }
    }
  },
  "paired_comparisons": {
    "GS1_vs_GB0": {
      "wins": 0,
      "losses": 0,
      "ties": 125,
      "missing": 0
    },
    "GS2_vs_GS1": {
      "wins": 1,
      "losses": 0,
      "ties": 124,
      "missing": 0
    },
    "GS2H_vs_GS2": {
      "wins": 0,
      "losses": 1,
      "ties": 124,
      "missing": 0
    },
    "GS2HR_vs_GS2H": {
      "wins": 1,
      "losses": 0,
      "ties": 124,
      "missing": 0
    },
    "GS3_vs_GS2HR": {
      "wins": 57,
      "losses": 0,
      "ties": 68,
      "missing": 0
    },
    "V3Q_vs_GS3": {
      "wins": 12,
      "losses": 13,
      "ties": 100,
      "missing": 0
    },
    "V3F_vs_V3Q": {
      "wins": 1,
      "losses": 65,
      "ties": 59,
      "missing": 0
    }
  },
  "diagnostics": {
    "GB0": {
      "ok": 63,
      "page_miss": 30,
      "ranking_miss": 26,
      "file_recall_miss": 6
    },
    "GS1": {
      "ok": 63,
      "page_miss": 30,
      "ranking_miss": 26,
      "file_recall_miss": 6
    },
    "GS2": {
      "ok": 85,
      "page_miss": 24,
      "ranking_miss": 16
    },
    "GS2H": {
      "ok": 77,
      "page_miss": 31,
      "ranking_miss": 17
    },
    "GS2HR": {
      "ok": 94,
      "page_miss": 30,
      "ranking_miss": 1
    },
    "GS3": {
      "ok": 89,
      "page_miss": 26,
      "ranking_miss": 10
    },
    "V3F": {
      "ok": 35,
      "page_miss": 17,
      "ranking_miss": 3,
      "file_recall_miss": 70
    },
    "V3Q": {
      "ok": 96,
      "page_miss": 28,
      "ranking_miss": 1
    }
  },
  "build_fingerprint": {
    "git_commit": "2aaf11ba89e4447bab8d11a78ca44e09ece38e87",
    "git_status": [
      " M .omx/metrics.json",
      " M .omx/state/hud-state.json",
      " M .omx/state/notify-hook-state.json",
      " M .omx/state/tmux-hook-state.json",
      " D RAG_DIAGNOSTIC_SPEC.md",
      " D RAG_HIERARCHICAL_V1_DESIGN.md",
      " D RAG_HIERARCHICAL_V1_EXPERIMENT_MATRIX.md",
      " D SUPERHERMES_UI_REDESIGN_PLAN.md",
      " M backend/__init__.py",
      " M backend/answer_eval.py",
      " M backend/milvus_client.py",
      " M backend/rag_pipeline.py",
      " M backend/rag_utils.py",
      " M backend/tools.py",
      " M docs/rag-v3.1-task-board.md",
      " D main.py",
      " M pyproject.toml",
      " M scripts/evaluate_rag_matrix.py",
      " D test_embedding.py",
      " D test_langsmith_eval.py",
      " M uv.lock",
      "?? .jbeval/qrel_reviews/",
      "?? .jbeval/qrels/",
      "?? .jbeval/reports/debug-gb0-worker.jsonl",
      "?? .jbeval/reports/gpu-worker-debug.jsonl",
      "?? .jbeval/reports/rag-boundary-qrels-smoke-20260425/",
      "?? .jbeval/reports/rag-boundary-qrels-v2-smoke-20260425/",
      "?? .jbeval/reports/rag-v3.1-full-gold-20260425-161459/",
      "?? .jbeval/reports/rag-v3.1-full-gold-final-20260425-182251/",
      "?? .jbeval/reports/rag-v3.1-v3-only-20260425-172143/",
      "?? .jbeval/reports/rag-v3.1-v3f-diagnosis-20260426/",
      "?? .jbeval/reports/rag-v4-full-gold-rerun/",
      "?? .jbeval/reports/rag-v4-full-gold/",
      "?? .jbeval/reports/rag-v4-gpu-mode-smoke/",
      "?? .jbeval/reports/rag-v4-post-s3-default-smoke/",
      "?? .jbeval/reports/rag-v4-post-s3-v2-smoke/",
      "?? .jbeval/reports/regression-a-20260426/",
      "?? .jbeval/reports/saved-row-regression-smoke-20260425-refactor/",
      "?? .jbeval/reports/saved-row-regression-variants-extract-20260426/",
      "?? .jbeval/run_logs/",
      "?? .omx/logs/tmux-hook-2026-04-25.jsonl",
      "?? .omx/logs/tmux-hook-2026-04-26.jsonl",
      "?? .omx/logs/turns-2026-04-25.jsonl",
      "?? .omx/logs/turns-2026-04-26.jsonl",
      "?? docs/ARCHITECTURE.md",
      "?? docs/archive/",
      "?? docs/superpowers/specs/2026-04-26-rag-v3.1-closure-design.md",
      "?? scripts/diagnose_variant_profile.py",
      "?? scripts/rag_eval/io.py",
      "?? scripts/rag_eval/preflight.py",
      "?? scripts/rag_eval/reporting.py",
      "?? scripts/rag_eval/variants.py",
      "?? scripts/review_rag_qrels.py",
      "?? tests/test_diagnose_variant_profile.py",
      "?? tests/test_review_rag_qrels.py"
    ],
    "source_results_jsonl": "C:\\Users\\goahe\\Desktop\\Project\\SuperHermes\\.jbeval\\reports\\rag-v3.1-full-gold-qrels-refactor-20260426\\results.jsonl",
    "source_results_sha256": "59378a6d5dcaede16d5f258864cc44f93e5d5f73ff746cbc468a33899d1188e6",
    "variants": [
      "GB0",
      "GS1",
      "GS2",
      "GS2H",
      "GS2HR",
      "GS3",
      "V3F",
      "V3Q"
    ],
    "mode": "saved_results_summary"
  },
  "qrel_contract": {
    "mode": "saved_results_summary",
    "source_results_jsonl": "C:\\Users\\goahe\\Desktop\\Project\\SuperHermes\\.jbeval\\reports\\rag-v3.1-full-gold-qrels-refactor-20260426\\results.jsonl"
  }
}