{
  "status": "excluded_from_baseline",
  "reason": "v3f_rebuild_blocked_or_unstable",
  "v3f": {
    "file_at_5": 0.416,
    "file_cand_recall": 0.44,
    "p50_ms": 33.97509999922477,
    "p95_ms": 3047.0336999977008,
    "error_rate": 0.0
  },
  "gs3_ref": {
    "file_at_5": 0.92,
    "file_cand_recall": 1.0,
    "p50_ms": 1144.175900000846,
    "p95_ms": 1609.5243599935202,
    "error_rate": 0.0
  },
  "gate": {
    "target_file_cand_recall": 0.95,
    "target_file_at_5": 0.85,
    "target_error_rate": 0.0,
    "target_p50_ratio_lt_gs3": 0.75
  },
  "notes": [
    "Multiple rebuild attempts stalled in Milvus reindex stage",
    "Current V3F metrics do not satisfy release gates",
    "Proceed with GS3 as baseline, V3Q as quality ceiling/fallback candidate"
  ]
}